README.rst
setup.py
resources/__init__.py
resources/client.py
resources/manager.py
resources/resource.py
resources.egg-info/PKG-INFO
resources.egg-info/SOURCES.txt
resources.egg-info/dependency_links.txt
resources.egg-info/top_level.txt