Metadata-Version: 1.1
Name: resources
Version: 0.0.1
Summary: Resource centered REST API clients
Home-page: https://github.com/lamenezes/resource
Author: Luiz Menezes
Author-email: luiz.menezesf@gmail.com
License: MIT
Download-URL: https://github.com/lamenezes/resource/releases
Keywords: django resource api model microservices client request lazy
Platform: UNKNOWN
Classifier: Development Status :: 3 - Alpha
Classifier: Intended Audience :: Developers
Classifier: Programming Language :: Python :: 3 :: Only
Classifier: Programming Language :: Python :: 3.5
Classifier: Programming Language :: Python :: 3.6
Classifier: License :: OSI Approved :: MIT License
Classifier: Natural Language :: English
Classifier: Operating System :: OS Independent
